mcvqoe/psud/PSuD.py
mcvqoe/psud/PSuD_1way_1loc.py
mcvqoe/psud/PSuD_eval.py
mcvqoe/psud/PSuD_reprocess.py
mcvqoe/psud/PSuD_simulate.py
mcvqoe/psud/__init__.py
mcvqoe/psud/sweep_methods.py
mcvqoe/psud/version.py
mcvqoe/psud/audio_clips/set1/F1_n10_s1_c1.csv
mcvqoe/psud/audio_clips/set1/F1_n10_s1_c1.wav
mcvqoe/psud/audio_clips/set1/F1_n10_s1_c10.csv
mcvqoe/psud/audio_clips/set1/F1_n10_s1_c10.wav
mcvqoe/psud/audio_clips/set1/F1_n10_s1_c11.csv
mcvqoe/psud/audio_clips/set1/F1_n10_s1_c11.wav
mcvqoe/psud/audio_clips/set1/F1_n10_s1_c12.csv
mcvqoe/psud/audio_clips/set1/F1_n10_s1_c12.wav
mcvqoe/psud/audio_clips/set1/F1_n10_s1_c13.csv
mcvqoe/psud/audio_clips/set1/F1_n10_s1_c13.wav
mcvqoe/psud/audio_clips/set1/F1_n10_s1_c14.csv
mcvqoe/psud/audio_clips/set1/F1_n10_s1_c14.wav
mcvqoe/psud/audio_clips/set1/F1_n10_s1_c15.csv
mcvqoe/psud/audio_clips/set1/F1_n10_s1_c15.wav
mcvqoe/psud/audio_clips/set1/F1_n10_s1_c16.csv
mcvqoe/psud/audio_clips/set1/F1_n10_s1_c16.wav
mcvqoe/psud/audio_clips/set1/F1_n10_s1_c17.csv
mcvqoe/psud/audio_clips/set1/F1_n10_s1_c17.wav
mcvqoe/psud/audio_clips/set1/F1_n10_s1_c18.csv
mcvqoe/psud/audio_clips/set1/F1_n10_s1_c18.wav
mcvqoe/psud/audio_clips/set1/F1_n10_s1_c19.csv
mcvqoe/psud/audio_clips/set1/F1_n10_s1_c19.wav
mcvqoe/psud/audio_clips/set1/F1_n10_s1_c2.csv
mcvqoe/psud/audio_clips/set1/F1_n10_s1_c2.wav
mcvqoe/psud/audio_clips/set1/F1_n10_s1_c20.csv
mcvqoe/psud/audio_clips/set1/F1_n10_s1_c20.wav
mcvqoe/psud/audio_clips/set1/F1_n10_s1_c21.csv
mcvqoe/psud/audio_clips/set1/F1_n10_s1_c21.wav
mcvqoe/psud/audio_clips/set1/F1_n10_s1_c22.csv
mcvqoe/psud/audio_clips/set1/F1_n10_s1_c22.wav
mcvqoe/psud/audio_clips/set1/F1_n10_s1_c23.csv
mcvqoe/psud/audio_clips/set1/F1_n10_s1_c23.wav
mcvqoe/psud/audio_clips/set1/F1_n10_s1_c24.csv
mcvqoe/psud/audio_clips/set1/F1_n10_s1_c24.wav
mcvqoe/psud/audio_clips/set1/F1_n10_s1_c25.csv
mcvqoe/psud/audio_clips/set1/F1_n10_s1_c25.wav
mcvqoe/psud/audio_clips/set1/F1_n10_s1_c26.csv
mcvqoe/psud/audio_clips/set1/F1_n10_s1_c26.wav
mcvqoe_psud-1.1.3.dist-info/LICENSE.md
mcvqoe_psud-1.1.3.dist-info/METADATA
mcvqoe_psud-1.1.3.dist-info/WHEEL
mcvqoe_psud-1.1.3.dist-info/entry_points.txt
mcvqoe_psud-1.1.3.dist-info/top_level.txt
mcvqoe_psud-1.1.3.dist-info/RECORD
